pytruncreg/__init__.py
pytruncreg/truncreg.py
pytruncreg-1.0.1.dist-info/licenses/LICENSE
pytruncreg-1.0.1.dist-info/METADATA
pytruncreg-1.0.1.dist-info/WHEEL
pytruncreg-1.0.1.dist-info/top_level.txt
pytruncreg-1.0.1.dist-info/RECORD
