Metadata-Version: 2.4
Name: pytruncreg
Version: 1.0.1
Summary: Truncated Gaussian Regression Models
Home-page: https://github.com/CausalInference/pytruncreg
Author: Ryan ODea
Author-email: ryan.odea@psi.ch
License-File: LICENSE
Requires-Dist: numpy
Requires-Dist: scipy
Requires-Dist: pandas
Dynamic: author
Dynamic: author-email
Dynamic: description
Dynamic: description-content-type
Dynamic: home-page
Dynamic: license-file
Dynamic: requires-dist
Dynamic: summary
